Proton/__init__.py
ProtonPySDK-0.1.1.dist-info/METADATA
ProtonPySDK-0.1.1.dist-info/WHEEL
ProtonPySDK-0.1.1.dist-info/top_level.txt
ProtonPySDK-0.1.1.dist-info/RECORD
