Metadata-Version: 2.1
Name: ProtonPySDK
Version: 0.1.1
Summary: Proton SDK In Python (P+)
Home-page: UNKNOWN
Author: HanzHaxors, Seth A. Robinson
Author-email: hanzhaxors@gmail.com, seth@rtsoft.com
License: UNKNOWN
Platform: UNKNOWN
Classifier: Development Status :: 1 - Planning
Classifier: Intended Audience :: Developers
Classifier: Intended Audience :: End Users/Desktop
Classifier: License :: Free To Use But Restricted
